diffusive_solver/__init__.py
diffusive_solver/diffusive_solver.py
diffusive_solver/fenics_cookbook.py
diffusive_solver-3.0.dist-info/LICENSE.txt
diffusive_solver-3.0.dist-info/METADATA
diffusive_solver-3.0.dist-info/WHEEL
diffusive_solver-3.0.dist-info/top_level.txt
diffusive_solver-3.0.dist-info/RECORD
