Metadata-Version: 2.1
Name: diffusive-solver
Version: 3.0
Summary: Package for solving systems of coupled diffusion equations
Home-page: https://gitlab.com/itorre/diffusive_solver
Author: Iacopo Torre
Author-email: iacopo.torre@icfo.eu
License: UNKNOWN
Platform: UNKNOWN
Classifier: Programming Language :: Python :: 3
Classifier: License :: OSI Approved :: GNU Lesser General Public License v3 (LGPLv3)
Classifier: Operating System :: OS Independent
Classifier: Intended Audience :: Science/Research
Requires-Python: >=3.6
Requires-Dist: numpy
Requires-Dist: matplotlib
Requires-Dist: meshio
